karoto/__init__.py
karoto/backend.py
karoto/base_feed.py
karoto/clickable_label.py
karoto/error_bar.py
karoto/flow_layout.py
karoto/main.py
karoto/shopping_feed.py
karoto/storage_feed.py
karoto/style.py
karoto/tags.py
karoto-0.2.dist-info/LICENSE.MIT
karoto-0.2.dist-info/LICENSE.anarchist.md
karoto-0.2.dist-info/METADATA
karoto-0.2.dist-info/WHEEL
karoto-0.2.dist-info/entry_points.txt
karoto-0.2.dist-info/RECORD
