Metadata-Version: 2.1
Name: karoto
Version: 0.2
Summary: A shopping list app for Linux Mobile
Keywords: shopping,list,carrot,storage,stock,management,cart,basket
Author: DrRac27
Author-email: drrac27@riseup.net
Requires-Python: >=3.10,<4.0
Classifier: License :: OSI Approved :: MIT License
Classifier: Programming Language :: Python
Classifier: Programming Language :: Python :: 3
Classifier: Programming Language :: Python :: 3.10
Classifier: Programming Language :: Python :: 3.11
Requires-Dist: pyqt6 (>=6.4.2,<7.0.0)
